viperkernel/__init__.py
viperkernel/_viperkernel.py
viperkernel-1.0.0.dist-info/LICENSE
viperkernel-1.0.0.dist-info/METADATA
viperkernel-1.0.0.dist-info/WHEEL
viperkernel-1.0.0.dist-info/top_level.txt
viperkernel-1.0.0.dist-info/RECORD
