Metadata-Version: 2.2
Name: viperkernel
Version: 1.0.0
Summary: A package to perform VIPER-based velocity in Python
Home-page: https://github.com/alexanderlewis99/VIPERKernel/
Author: Alexander L.E. Wang
Author-email: aw3436@cumc.columbia.edu
License: MIT
Requires-Python: >=3.8
License-File: LICENSE
Requires-Dist: cellrank
Requires-Dist: tqdm
Requires-Dist: numpy
Dynamic: author
Dynamic: author-email
Dynamic: description
Dynamic: description-content-type
Dynamic: home-page
Dynamic: license
Dynamic: requires-dist
Dynamic: requires-python
Dynamic: summary
